libcloud_driver_kamatera/__init__.py
libcloud_driver_kamatera/kamatera.py
libcloud_driver_kamatera-0.0.2.dist-info/LICENSE
libcloud_driver_kamatera-0.0.2.dist-info/METADATA
libcloud_driver_kamatera-0.0.2.dist-info/WHEEL
libcloud_driver_kamatera-0.0.2.dist-info/top_level.txt
libcloud_driver_kamatera-0.0.2.dist-info/RECORD
