Metadata-Version: 2.1
Name: libcloud-driver-kamatera
Version: 0.0.2
Summary: Apache Libcloud driver for managing Kamatera compute resources
Home-page: https://github.com/Kamatera/libcloud-driver-kamatera
Author: Kamatera
License: MIT
Platform: UNKNOWN
Requires-Dist: apache-libcloud (>=2.8.2)
